mapply/__init__.py
mapply/_groupby.py
mapply/mapply.py
mapply/parallel.py
mapply-0.1.30.dist-info/licenses/LICENSE
mapply-0.1.30.dist-info/METADATA
mapply-0.1.30.dist-info/WHEEL
mapply-0.1.30.dist-info/top_level.txt
mapply-0.1.30.dist-info/RECORD
