Metadata-Version: 2.4
Name: mapply
Version: 0.1.30
Summary: Sensible multi-core apply function for Pandas
Author-email: ddelange <ddelange@delange.dev>
License-Expression: BSD-3-Clause
Project-URL: Repository, https://github.com/ddelange/mapply
Project-URL: Documentation, https://mapply.readthedocs.io
Classifier: Development Status :: 5 - Production/Stable
Classifier: Intended Audience :: Developers
Classifier: Operating System :: OS Independent
Classifier: Programming Language :: Python
Classifier: Programming Language :: Python :: 3
Classifier: Programming Language :: Python :: 3.9
Classifier: Programming Language :: Python :: 3.10
Classifier: Programming Language :: Python :: 3.11
Classifier: Programming Language :: Python :: 3.12
Classifier: Programming Language :: Python :: 3.13
Classifier: Topic :: Software Development :: Libraries :: Python Modules
Classifier: Topic :: Utilities
Requires-Python: >=3.9
License-File: LICENSE
Requires-Dist: pathos>=0.3.1
Requires-Dist: multiprocess
Requires-Dist: psutil
Requires-Dist: tqdm>=4.27
Requires-Dist: pandas~=2.1
Dynamic: license-file
